CHANGES.rst
LICENSE.txt
MANIFEST.in
README.rst
development.ini
production.ini
setup.cfg
setup.py
convertit/__init__.py
convertit/helpers.py
convertit/views.py
convertit.egg-info/PKG-INFO
convertit.egg-info/SOURCES.txt
convertit.egg-info/dependency_links.txt
convertit.egg-info/entry_points.txt
convertit.egg-info/not-zip-safe
convertit.egg-info/requires.txt
convertit.egg-info/top_level.txt
convertit/converted/logo-geotrek.png
convertit/converters/__init__.py
convertit/converters/inkscape.py
convertit/converters/unoconv.py
convertit/static/favicon.ico
convertit/static/footerbg.png
convertit/static/headerbg.png
convertit/static/ie6.css
convertit/static/middlebg.png
convertit/static/pylons.css
convertit/static/pyramid-small.png
convertit/static/pyramid.png
convertit/static/transparent.gif
convertit/templates/mytemplate.pt
convertit/tests/__init__.py
convertit/tests/test_functional.py
convertit/tests/test_helpers.py
convertit/tests/test_views.py
convertit/tests/converters/__init__.py
convertit/tests/converters/test_inkscape.py
convertit/tests/converters/test_unoconv.py