Metadata-Version: 2.1
Name: convertit
Version: 2.2.0
Summary: A file conversion Web API in Pyramid
Home-page: https://github.com/makinacorpus/convertit
Author: Makina Corpus
Author-email: python@makina-corpus.org
License: AGPLV3
Keywords: web pyramid webservice convert
Platform: UNKNOWN
Classifier: License :: OSI Approved :: GNU Affero General Public License v3
Classifier: Programming Language :: Python
Classifier: Framework :: Pylons
Classifier: Topic :: Internet :: WWW/HTTP
Classifier: Topic :: Internet :: WWW/HTTP :: WSGI :: Application
Provides-Extra: test
